pysagec/__init__.py
pysagec/base.py
pysagec/client.py
pysagec/models.py
pysagec/parsers.py
pysagec/renderers.py
pysagec/utils.py
pysagec-0.1.2.dist-info/DESCRIPTION.rst
pysagec-0.1.2.dist-info/METADATA
pysagec-0.1.2.dist-info/RECORD
pysagec-0.1.2.dist-info/WHEEL
pysagec-0.1.2.dist-info/metadata.json
pysagec-0.1.2.dist-info/top_level.txt
