Metadata-Version: 2.0
Name: pysagec
Version: 0.1.2
Summary: Python client to SAGEC MRW webservices.
Home-page: https://github.com/migonzalvar/pysagec
Author: Miguel Gonzalez
Author-email: migonzalvar@gmail.com
License: MIT
Platform: any
Classifier: Intended Audience :: Developers
Classifier: License :: OSI Approved :: MIT License
Classifier: Operating System :: OS Independent
Classifier: Programming Language :: Python
Classifier: Programming Language :: Python :: 3
Classifier: Topic :: Software Development :: Libraries :: Python Modules
